{
  "type": "minecraft:block",
  "pools": [
    {
      "rolls": 3,
      "entries": [
        {
          "type": "minecraft:item",
          "name": "minecraft:diamond",
          "count": 7
        },
        {
          "type": "minecraft:item",
          "name": "minecraft:gold_ingot",
          "functions": [
            {
              "function": "minecraft:set_count",
              "count": {
                "min": 11,
                "max": 19
              }
            }
          ]
        },
        {
          "type": "minecraft:item",
          "name": "minecraft:emerald",
          "functions": [
            {
              "function": "minecraft:set_count",
              "count": {
                "min": 6,
                "max": 9
              }
            }
          ]
        },
        {
          "type": "minecraft:item",
          "name": "minecraft:golden_apple",
          "functions": [
            {
              "function": "minecraft:set_count",
              "count": {
                "min": 1,
                "max": 3
              }
            }
          ]
        },
        {
          "type": "minecraft:item",
          "name": "minecraft:ender_pearl",
          "functions": [
            {
              "function": "minecraft:set_count",
              "count": {
                "min": 3,
                "max": 6
              }
            }
          ]
        },
        {
          "type": "minecraft:item",
          "name": "minecraft:blaze_rod",
          "functions": [
            {
              "function": "minecraft:set_count",
              "count": {
                "min": 2,
                "max": 5
              }
            }
          ]
        },
        {
          "type": "minecraft:item",
          "name": "noez:moonsilver_ingot",
          "functions": [
            {
              "function": "minecraft:set_count",
              "count": {
                "min": 7,
                "max": 11
              }
            }
          ]
        },
        {
          "type": "minecraft:item",
          "name": "noez:soul",
          "functions": [
            {
              "function": "minecraft:set_count",
              "count": {
                "min": 5,
                "max": 9
              }
            }
          ]
        },
        {
          "type": "minecraft:item",
          "name": "noez:vital_wrap",
          "functions": [
            {
              "function": "minecraft:set_count",
              "count": {
                "min": 5,
                "max": 8
              }
            }
          ]
        },
        {
          "type": "minecraft:item",
          "name": "minecraft:amethyst_shard",
          "functions": [
            {
              "function": "minecraft:set_count",
              "count": {
                "min": 4,
                "max": 7
              }
            }
          ]
        }
      ]
    }
  ]
}
